mcp_mixpanel/__init__.py
mcp_mixpanel/server.py
mcp_mixpanel-0.0.2.dist-info/METADATA
mcp_mixpanel-0.0.2.dist-info/WHEEL
mcp_mixpanel-0.0.2.dist-info/entry_points.txt
mcp_mixpanel-0.0.2.dist-info/top_level.txt
mcp_mixpanel-0.0.2.dist-info/RECORD
